wdc/__init__.py
wdc/calculator.py
wdc/classes.py
wdc/exceptions.py
wdc/runner.py
wdc/settings.py
wdc/time.py
wdc/controller/export_import.py
wdc/controller/work_day.py
wdc/helper/hash.py
wdc/helper/io.py
wdc-0.4.12.dist-info/LICENSE
wdc-0.4.12.dist-info/METADATA
wdc-0.4.12.dist-info/WHEEL
wdc-0.4.12.dist-info/entry_points.txt
wdc-0.4.12.dist-info/top_level.txt
wdc-0.4.12.dist-info/RECORD
