Metadata-Version: 2.1
Name: wdc
Version: 0.4.12
Summary: Command line work day helper and logger
Home-page: https://github.com/dejanfajfar/wdc
Author: Dejan Fajfar
Author-email: dejan@fajfar.com
License: UNKNOWN
Platform: UNKNOWN
Classifier: Development Status :: 3 - Alpha
Classifier: Environment :: Console
Classifier: Intended Audience :: End Users/Desktop
Classifier: Topic :: Utilities
Classifier: Natural Language :: English
Classifier: License :: OSI Approved :: GNU General Public License (GPL)
Requires-Dist: click
Requires-Dist: termtables
Requires-Dist: colored
